kabutobashi/__init__.py
kabutobashi/application/__init__.py
kabutobashi/application/analysis_application.py
kabutobashi/application/applications.py
kabutobashi/application/crawl_application.py
kabutobashi/domain/__init__.py
kabutobashi/domain/entity/__init__.py
kabutobashi/domain/entity/blocks/__init__.py
kabutobashi/domain/entity/blocks/basis_blocks.py
kabutobashi/domain/entity/blocks/crawl_blocks/__init__.py
kabutobashi/domain/entity/blocks/crawl_blocks/abc_crawl_block.py
kabutobashi/domain/entity/blocks/crawl_blocks/crawl_stock_info_block.py
kabutobashi/domain/entity/blocks/crawl_blocks/crawl_stock_info_multiple_days_block.py
kabutobashi/domain/entity/blocks/crawl_blocks/crawl_stock_ipo_block.py
kabutobashi/domain/entity/blocks/decorator.py
kabutobashi/domain/entity/blocks/extract_blocks/__init__.py
kabutobashi/domain/entity/blocks/extract_blocks/extract_stock_info_block.py
kabutobashi/domain/entity/blocks/extract_blocks/extract_stock_info_multiple_days_block.py
kabutobashi/domain/entity/blocks/extract_blocks/extract_stock_ipo_block.py
kabutobashi/domain/entity/blocks/parameterize_blocks/__init__.py
kabutobashi/domain/entity/blocks/parameterize_blocks/abc_parameterize_block.py
kabutobashi/domain/entity/blocks/parameterize_blocks/parameterize_adx_block.py
kabutobashi/domain/entity/blocks/parameterize_blocks/parameterize_bollinger_bands_block.py
kabutobashi/domain/entity/blocks/parameterize_blocks/parameterize_macd_block.py
kabutobashi/domain/entity/blocks/parameterize_blocks/parameterize_momentum_block.py
kabutobashi/domain/entity/blocks/parameterize_blocks/parameterize_pct_change.py
kabutobashi/domain/entity/blocks/parameterize_blocks/parameterize_psycho_logical_block.py
kabutobashi/domain/entity/blocks/parameterize_blocks/parameterize_sma_block.py
kabutobashi/domain/entity/blocks/parameterize_blocks/parameterize_stochastics_block.py
kabutobashi/domain/entity/blocks/parameterize_blocks/parameterize_volatility.py
kabutobashi-0.8.7.dist-info/LICENSE
kabutobashi-0.8.7.dist-info/METADATA
kabutobashi-0.8.7.dist-info/WHEEL
kabutobashi-0.8.7.dist-info/RECORD
