Metadata-Version: 2.1
Name: kabutobashi
Version: 0.8.7
Summary: Analyze stock
Home-page: https://github.com/gsy0911/kabutobashi
License: MIT
Keywords: stock
Author: yoshiki
Author-email: yoshiki0911@gmail.com
Requires-Python: >=3.10,<3.13
Classifier: License :: OSI Approved :: MIT License
Classifier: Programming Language :: Python :: 3
Classifier: Programming Language :: Python :: 3.10
Classifier: Programming Language :: Python :: 3.11
Classifier: Programming Language :: Python :: 3.12
Requires-Dist: beautifulsoup4 (>=4.12.3,<5.0.0)
Requires-Dist: httpx (>=0.27.0,<0.28.0)
Requires-Dist: jpholiday (>=0.1.10,<0.2.0)
Requires-Dist: lxml (>=5.3.0,<6.0.0)
Requires-Dist: pandas (>=2.2.2,<3.0.0)
Requires-Dist: pydantic (>=2.7.1,<3.0.0)
Requires-Dist: scipy (>=1.11.3,<2.0.0)
Requires-Dist: xlrd (>=2.0.1,<3.0.0)
Project-URL: Repository, https://github.com/gsy0911/kabutobashi
